CHANGES.rst
LICENSE
MANIFEST.in
README.rst
setup.cfg
setup.py
dogpile_elasticache/__init__.py
dogpile_elasticache/backends.py
dogpile_elasticache/cluster.py
dogpile_elasticache.egg-info/PKG-INFO
dogpile_elasticache.egg-info/SOURCES.txt
dogpile_elasticache.egg-info/dependency_links.txt
dogpile_elasticache.egg-info/entry_points.txt
dogpile_elasticache.egg-info/requires.txt
dogpile_elasticache.egg-info/top_level.txt
dogpile_elasticache/tests/__init__.py
dogpile_elasticache/tests/test_cluster.py
dogpile_elasticache/tests/test_pymemcache.py