Metadata-Version: 1.1
Name: dogpile-elasticache
Version: 0.1
Summary: Dogpile backend for AWS Elasticache Memcache service
Home-page: https://github.com/ludia/dogpile_elasticache
Author: Pior Bastida
Author-email: pbastida@ludia.com
License: MIT
Keywords: dogpile cache aws elasticache memcache
Platform: UNKNOWN
Classifier: Intended Audience :: Developers
Classifier: License :: OSI Approved :: MIT License
Classifier: Operating System :: POSIX :: Linux
Classifier: Programming Language :: Python
Classifier: Programming Language :: Python :: 2.7
